LICENSE
README.md
setup.py
pypmml_spark/__init__.py
pypmml_spark/link_pmml4s_jars_into_spark.py
pypmml_spark/score_model.py
pypmml_spark/version.py
pypmml_spark.egg-info/PKG-INFO
pypmml_spark.egg-info/SOURCES.txt
pypmml_spark.egg-info/dependency_links.txt
pypmml_spark.egg-info/requires.txt
pypmml_spark.egg-info/top_level.txt
pypmml_spark/jars/__init__.py
pypmml_spark/jars/commons-lang3-3.15.0.jar
pypmml_spark/jars/commons-math3-3.6.1.jar
pypmml_spark/jars/commons-text-1.12.0.jar
pypmml_spark/jars/pmml4s-spark_2.12-1.5.3.jar
pypmml_spark/jars/pmml4s_2.12-1.5.5.jar
pypmml_spark/jars/spray-json_2.12-1.3.6.jar