Metadata-Version: 2.1
Name: pypmml-spark
Version: 1.5.5
Summary: Python PMML scoring library for PySpark as SparkML Transformer
Home-page: https://github.com/autodeployai/pypmml-spark
Download-URL: https://github.com/autodeployai/pypmml-spark/archive/v1.5.5.tar.gz
Author: AutoDeployAI
Author-email: autodeploy.ai@gmail.com
License: Apache License 2.0
Classifier: Development Status :: 5 - Production/Stable
Classifier: Environment :: Console
Classifier: Environment :: Web Environment
Classifier: Intended Audience :: Developers
Classifier: Intended Audience :: System Administrators
Classifier: License :: OSI Approved :: Apache Software License
Classifier: Operating System :: OS Independent
Classifier: Programming Language :: Python :: 2.7
Classifier: Programming Language :: Python :: 3
Classifier: Programming Language :: Python :: 3.5
Classifier: Programming Language :: Python :: 3.6
Classifier: Programming Language :: Python :: 3.7
Classifier: Programming Language :: Python :: 3.8
Classifier: Programming Language :: Python :: 3.9
Classifier: Programming Language :: Python :: 3.10
Classifier: Programming Language :: Python :: 3.11
Classifier: Topic :: Scientific/Engineering :: Artificial Intelligence
License-File: LICENSE
Requires-Dist: pyspark>=3.0.0
